collageradiomicstypes.py
collageradiomicstypes-0.2.1.dev26.dist-info/LICENSE
collageradiomicstypes-0.2.1.dev26.dist-info/METADATA
collageradiomicstypes-0.2.1.dev26.dist-info/WHEEL
collageradiomicstypes-0.2.1.dev26.dist-info/top_level.txt
collageradiomicstypes-0.2.1.dev26.dist-info/RECORD
