Metadata-Version: 2.1
Name: collageradiomicstypes
Version: 0.2.1.dev26
Summary: CoLliage Implementation
Home-page: https://github.com/radxtools/collageradiomics
Author: Toth Technology
Author-email: toth-tech@hillyer.me
License: UNKNOWN
Project-URL: Docker Examples, https://hub.docker.com/repository/docker/ccipd/collageradiomics-examples
Project-URL: Docker Module, https://hub.docker.com/repository/docker/ccipd/collageradiomics-pip
Project-URL: GitHub, https://github.com/radxtools/collageradiomics
Keywords: radiomics cancerimaging medicalresearch computationalimaging
Platform: UNKNOWN
Classifier: Development Status :: 3 - Alpha
Classifier: Intended Audience :: Science/Research
Classifier: Intended Audience :: Developers
Classifier: License :: OSI Approved :: BSD License
Classifier: Operating System :: OS Independent
Classifier: Operating System :: POSIX :: Linux
Classifier: Operating System :: Microsoft :: Windows :: Windows 10
Classifier: Operating System :: MacOS
Classifier: Programming Language :: Python :: 3
Classifier: Topic :: Scientific/Engineering :: Bio-Informatics
Requires-Python: >=3.6
